easyofd/__init__.py
easyofd/ofd.py
easyofd/draw/__init__.py
easyofd/draw/draw_ofd.py
easyofd/draw/draw_pdf.py
easyofd/draw/find_seal_img.py
easyofd/draw/font_tools.py
easyofd/draw/ofdtemplate.py
easyofd/draw/pdf_parse.py
easyofd/parser_ofd/__init__.py
easyofd/parser_ofd/file_annotation_parser.py
easyofd/parser_ofd/file_attachment_parser.py
easyofd/parser_ofd/file_content_parser.py
easyofd/parser_ofd/file_customtag_parser.py
easyofd/parser_ofd/file_deal.py
easyofd/parser_ofd/file_doc_parser.py
easyofd/parser_ofd/file_docres_parser.py
easyofd/parser_ofd/file_ofd_parser.py
easyofd/parser_ofd/file_parser.py
easyofd/parser_ofd/file_parser_base.py
easyofd/parser_ofd/file_publicres_parser.py
easyofd/parser_ofd/file_signature_parser.py
easyofd/parser_ofd/find_seal_img.py
easyofd/parser_ofd/img_deal.py
easyofd/parser_ofd/ofd_parser.py
easyofd/parser_ofd/parameter_parser.py
easyofd/parser_ofd/path_parser.py
easyofd/template_ofd/__init__.py
easyofd/template_ofd/ofdtemplate.py
easyofd-0.5.6.dist-info/licenses/LICENSE
easyofd-0.5.6.dist-info/METADATA
easyofd-0.5.6.dist-info/WHEEL
easyofd-0.5.6.dist-info/top_level.txt
easyofd-0.5.6.dist-info/RECORD
