Metadata-Version: 2.4
Name: easyofd
Version: 0.5.6
Summary: easy operate OFD
Home-page: https://github.com/renoyuan/easyofd
Author: renoyuan
Author-email: renoyuan@foxmail.com
Classifier: Programming Language :: Python :: 3
Classifier: License :: OSI Approved :: Apache Software License
Classifier: Operating System :: OS Independent
Requires-Python: >=3.8
License-File: LICENSE
Requires-Dist: reportlab>=3.6.11
Requires-Dist: xmltodict>=0.13.0
Requires-Dist: loguru>=0.7.2
Requires-Dist: fontTools>=4.43.1
Requires-Dist: PyMuPDF>=1.23.4
Requires-Dist: pyasn1>=0.6.0
Dynamic: author
Dynamic: author-email
Dynamic: classifier
Dynamic: description
Dynamic: description-content-type
Dynamic: home-page
Dynamic: license-file
Dynamic: requires-dist
Dynamic: requires-python
Dynamic: summary
